crypto_trading_mcp/__init__.py
crypto_trading_mcp/exceptions.py
crypto_trading_mcp/http_handler.py
crypto_trading_mcp/server.py
crypto_trading_mcp/utils.py
crypto_trading_mcp/exchanges/__init__.py
crypto_trading_mcp/exchanges/base.py
crypto_trading_mcp/exchanges/binance.py
crypto_trading_mcp/exchanges/factory.py
crypto_trading_mcp/exchanges/gateio.py
crypto_trading_mcp/exchanges/upbit.py
iflow_mcp_vkdnjznd_crypto_mcp-0.1.0.dist-info/METADATA
iflow_mcp_vkdnjznd_crypto_mcp-0.1.0.dist-info/WHEEL
iflow_mcp_vkdnjznd_crypto_mcp-0.1.0.dist-info/entry_points.txt
iflow_mcp_vkdnjznd_crypto_mcp-0.1.0.dist-info/licenses/LICENSE
iflow_mcp_vkdnjznd_crypto_mcp-0.1.0.dist-info/RECORD
