Metadata-Version: 2.4
Name: iflow-mcp_vkdnjznd_crypto_mcp
Version: 0.1.0
Summary: MCP Server for Trading Cryptocurrency
License-File: LICENSE
Requires-Python: >=3.10.16
Requires-Dist: black>=25.1.0
Requires-Dist: fastmcp>=2.1.0
Requires-Dist: httpx>=0.28.1
Requires-Dist: isort>=6.0.1
Requires-Dist: pydantic>=2.11.3
Requires-Dist: pyjwt>=2.10.1
Requires-Dist: python-dotenv>=1.1.0
Requires-Dist: pytz>=2025.2
Requires-Dist: sse-starlette>=2.2.1
Requires-Dist: starlette>=0.46.1
Requires-Dist: uvicorn>=0.34.0
Provides-Extra: dev
Requires-Dist: black>=25.1.0; extra == 'dev'
Requires-Dist: isort>=6.0.1; extra == 'dev'
Provides-Extra: test
Requires-Dist: pytest-asyncio>=0.26.0; extra == 'test'
Requires-Dist: pytest>=8.3.5; extra == 'test'
